prtg_sensor/__init__.py
prtg_sensor/sensor.py
prtg_sensor-1.0.1.dist-info/LICENSE
prtg_sensor-1.0.1.dist-info/METADATA
prtg_sensor-1.0.1.dist-info/WHEEL
prtg_sensor-1.0.1.dist-info/top_level.txt
prtg_sensor-1.0.1.dist-info/RECORD
