Metadata-Version: 2.1
Name: prtg-sensor
Version: 1.0.1
Summary: Simple data generator for advanced PRTG sensors
Home-page: https://github.com/maymon-max/prtg-sensor.git
Author: Max Maymon
License: MIT
Keywords: prtg,sensor,prtg custom sensor
Classifier: Programming Language :: Python
Classifier: Programming Language :: Python :: 3.7
Classifier: Programming Language :: Python :: 3.8
Classifier: Programming Language :: Python :: 3.9
Classifier: Programming Language :: Python :: 3.10
Classifier: Programming Language :: Python :: 3.11
License-File: LICENSE
